cli.py
pyberdrola/__init__.py
pyberdrola/pyberdrola.py
pyberdrola/utils.py
pyberdrola/tests/__init__.py
pyberdrola-0.0.12.dist-info/LICENSE
pyberdrola-0.0.12.dist-info/METADATA
pyberdrola-0.0.12.dist-info/WHEEL
pyberdrola-0.0.12.dist-info/entry_points.txt
pyberdrola-0.0.12.dist-info/top_level.txt
pyberdrola-0.0.12.dist-info/RECORD
