Metadata-Version: 2.1
Name: pyberdrola
Version: 0.0.12
Summary: A client to use www.iberdrola.es from the terminal
Home-page: https://github.com/patoroco/pyberdrola
Author: Jorge Maroto
Author-email: patoroco@gmail.com
License: UNKNOWN
Platform: UNKNOWN
Classifier: Programming Language :: Python :: 3
Classifier: License :: OSI Approved :: MIT License
Classifier: Operating System :: OS Independent
Requires-Dist: requests (==2.22.0)
